{
    "tcpreplay": [
        {
            "start_delay": 0,
            "duration": 60,
            "sender": "h1",
            "sender_opt": "--preload-pcap --stats=1 ../resources/workloads/bw/red.pcp",
            "sender_log": "red-s-h1-h14.txt",
            "receiver": "h14",
            "receiver_opt": "10.0.7.14 1234",
            "receiver_log": "red-r-h1-h14.txt"
        },
        {
            "start_delay": 0,
            "duration": 60,
            "sender": "h7",
            "sender_opt": "--preload-pcap --stats=1 ../resources/workloads/bw/blue.pcp",
            "sender_log": "blue-s-h7-h11.txt",
            "receiver": "h11",
            "receiver_opt": "10.0.6.11 1234",
            "receiver_log": "blue-r-h7-h11.txt"
        },
        {
            "start_delay": 0,
            "duration": 60,
            "sender": "h2",
            "sender_opt": "--preload-pcap --stats=1 ../resources/workloads/bw/teal.pcp",
            "sender_log": "teal-s-h2-h9.txt",
            "receiver": "h9",
            "receiver_opt": "10.0.5.9 1234",
            "receiver_log": "teal-r-h2-h9.txt"
        },
        {
            "start_delay": 0,
            "duration": 60,
            "sender": "h5",
            "sender_opt": "--preload-pcap --stats=1 ../resources/workloads/bw/green.pcp",
            "sender_log": "green-s-h5-h9.txt",
            "receiver": "h9",
            "receiver_opt": "10.0.5.9 1235",
            "receiver_log": "green-r-h5-h9.txt"
        },
        {
            "start_delay": 0,
            "duration": 60,
            "sender": "h6",
            "sender_opt": "--preload-pcap --stats=1 ../resources/workloads/bw/orange.pcp",
            "sender_log": "orange-s-h6-h13.txt",
            "receiver": "h13",
            "receiver_opt": "10.0.7.13 1234",
            "receiver_log": "orange-r-h6-h13.txt"
        }
    ]
}